ride_pfa/__init__.py
ride_pfa/centroid_graph/__init__.py
ride_pfa/centroid_graph/centroids_graph_builder.py
ride_pfa/clustering/__init__.py
ride_pfa/clustering/clustering.py
ride_pfa/drawer/__init__.py
ride_pfa/drawer/folium_drawer.py
ride_pfa/drawer/matplotlib_drawer.py
ride_pfa/exceptions.py
ride_pfa/graph_osm_loader.py
ride_pfa/heuristics.py
ride_pfa/path_finding/__init__.py
ride_pfa/path_finding/advenced_pfa.py
ride_pfa/path_finding/dijkstra_pfa.py
ride_pfa/path_finding/excraction_pfa.py
ride_pfa/path_finding/heuristic_pfa.py
ride_pfa/path_finding/pfa.py
ride_pfa/utils.py
ride_pfa-0.1.2.dist-info/LICENSE
ride_pfa-0.1.2.dist-info/METADATA
ride_pfa-0.1.2.dist-info/WHEEL
ride_pfa-0.1.2.dist-info/RECORD
