Metadata-Version: 2.3
Name: ride_pfa
Version: 0.1.2
Summary: 
Author: Your Name
Author-email: you@example.com
Requires-Python: >=3.10,<4.0
Classifier: Programming Language :: Python :: 3
Classifier: Programming Language :: Python :: 3.10
Classifier: Programming Language :: Python :: 3.11
Classifier: Programming Language :: Python :: 3.12
Classifier: Programming Language :: Python :: 3.13
Requires-Dist: contextily (>=1.6.2,<2.0.0)
Requires-Dist: folium (>=0.17.0,<0.18.0)
Requires-Dist: furo (>=2024.8.6,<2025.0.0)
Requires-Dist: geopandas (>=0.14.4,<0.15.0)
Requires-Dist: ipykernel (>=6.29.4,<7.0.0)
Requires-Dist: kmedoids (>=0.5.3.1,<0.6.0.0)
Requires-Dist: matplotlib (>=3.8.4,<4.0.0)
Requires-Dist: networkx (>=3.3,<4.0)
Requires-Dist: ortools (>=9.10.4067,<10.0.0)
Requires-Dist: osmnx (>=1.9.3,<2.0.0)
Requires-Dist: requests (>=2.31.0,<3.0.0)
Requires-Dist: scikit-learn (>=1.4.2,<2.0.0)
Requires-Dist: scipy (>=1.13.0,<2.0.0)
Requires-Dist: tqdm (>=4.66.4,<5.0.0)
